pylluvial/__init__.py
pylluvial/aggregate.py
pylluvial/fit.py
pylluvial/plot.py
pylluvial/stratum.py
pylluvial/utils.py
pylluvial-1.1.1.dist-info/LICENSE
pylluvial-1.1.1.dist-info/METADATA
pylluvial-1.1.1.dist-info/WHEEL
pylluvial-1.1.1.dist-info/top_level.txt
pylluvial-1.1.1.dist-info/RECORD
