Metadata-Version: 2.1
Name: pylluvial
Version: 1.1.1
Summary: Python package for plotting alluvial diagrams with an arbitrary number of layers
Author-email: Daniel Malzl <daniel@menchelab.com>
License: MIT License        
Project-URL: Homepage, https://github.com/dmalzl/pylluvial
Keywords: plotting,networks,analysis,alluvial-plot
Classifier: License :: OSI Approved :: MIT License
Classifier: Programming Language :: Python
Classifier: Programming Language :: Python :: 3
Requires-Python: >=3.9
License-File: LICENSE
Requires-Dist: matplotlib (>=3.5.2)
Requires-Dist: numpy (>=1.23.1)
Requires-Dist: pandas (>=1.4.3)
Requires-Dist: seaborn (>=0.11.2)
